accelbyte_py_sdk/api/dslogmanager/__init__.py
accelbyte_py_sdk/api/dslogmanager/errors.py
accelbyte_py_sdk/api/dslogmanager/models/__init__.py
accelbyte_py_sdk/api/dslogmanager/models/log_app_message_declaration.py
accelbyte_py_sdk/api/dslogmanager/models/models_allocation_event.py
accelbyte_py_sdk/api/dslogmanager/models/models_batch_download_logs_request.py
accelbyte_py_sdk/api/dslogmanager/models/models_download_logs_request.py
accelbyte_py_sdk/api/dslogmanager/models/models_list_terminated_servers_response.py
accelbyte_py_sdk/api/dslogmanager/models/models_log_file_status.py
accelbyte_py_sdk/api/dslogmanager/models/models_match_result.py
accelbyte_py_sdk/api/dslogmanager/models/models_metadata_servers_request.py
accelbyte_py_sdk/api/dslogmanager/models/models_notif_payload_server_status_change_response.py
accelbyte_py_sdk/api/dslogmanager/models/models_paging_cursor.py
accelbyte_py_sdk/api/dslogmanager/models/models_request_match_member.py
accelbyte_py_sdk/api/dslogmanager/models/models_request_match_party.py
accelbyte_py_sdk/api/dslogmanager/models/models_request_matching_ally.py
accelbyte_py_sdk/api/dslogmanager/models/models_server_logs.py
accelbyte_py_sdk/api/dslogmanager/models/models_server_response.py
accelbyte_py_sdk/api/dslogmanager/models/models_status_history.py
accelbyte_py_sdk/api/dslogmanager/models/response_error.py
accelbyte_py_sdk/api/dslogmanager/operations/__init__.py
accelbyte_py_sdk/api/dslogmanager/operations/admin/__init__.py
accelbyte_py_sdk/api/dslogmanager/operations/admin/get_server_logs.py
accelbyte_py_sdk/api/dslogmanager/operations/all_terminated_servers/__init__.py
accelbyte_py_sdk/api/dslogmanager/operations/all_terminated_servers/batch_download_server_logs.py
accelbyte_py_sdk/api/dslogmanager/operations/all_terminated_servers/list_all_terminated_servers.py
accelbyte_py_sdk/api/dslogmanager/operations/all_terminated_servers/list_metadata_servers.py
accelbyte_py_sdk/api/dslogmanager/operations/dslogmanager_operations/__init__.py
accelbyte_py_sdk_service_dslogmanager-0.14.0.dist-info/METADATA
accelbyte_py_sdk_service_dslogmanager-0.14.0.dist-info/WHEEL
accelbyte_py_sdk_service_dslogmanager-0.14.0.dist-info/top_level.txt
accelbyte_py_sdk_service_dslogmanager-0.14.0.dist-info/RECORD
