Metadata-Version: 2.4
Name: accelbyte-py-sdk-service-dslogmanager
Version: 0.14.0
Summary: AccelByte Python SDK - AccelByte Gaming Services Ds Log Manager Service
Requires-Python: >=3.9
Requires-Dist: accelbyte-py-sdk-core
